{"citations": ["6713770", "6718086", "6692899", "6192344", "7293240", "6693748", "6155633", "7375385", "6837511", "6953262", "6513323", "6665412", "6280592", "6574880", "6489422", "7123681", "6522545", "6578601", "6727437", "7031964", "7081388", "6403327", "7132796", "6305015", "6374325", "6725824", "6687822", "6687880", "6686931", "6476373"], "references": ["5457414", "1236482", "5325768", "4590576", "1332787", "1392524", "4463587", "5611945", "5505467", "4967843", "4639525", "5978236", "5481995", "5315625", "5677445", "5619653", "5619646", "5518016", "5514771", "5517225", "5516205", "5613743", "5012477", "5972828"], "details": {"publisher": "IEEE", "issue_date": "Nov. 2011", "doi": "10.1109/TTHZ.2011.2160021", "title": "All Active MMIC-Based Wireless Communication at 220 GHz", "abstract": null, "journal_title": "IEEE Transactions on Terahertz Science and Technology", "firstpage": "477", "volume": "1", "lastpage": "487", "date_publication": "Thu Aug 04 00:00:00 EDT 2011", "sponsor": "IEEE Microwave Theory and Techniques Society", "inspec": "12318421", "date": "Nov. 2011", "date_current_version": "Thu Oct 27 00:00:00 EDT 2011", "issue": "2", "pages": "477 - 487", "issn": "2156-342X"}, "authors": ["Ingmar Kallfass", "Jochen Antes", "Thomas Schneider", "Fabian Kurz", "Daniel Lopez-Diaz", "Sebastian Diebold", "Hermann Massler", "Arnulf Leuther", "Axel Tessmann"], "keywords": ["MMIC", "error statistics", "quadrature amplitude modulation", "active MMIC-based wireless communication", "active multifunctional millimeter-wave microwave integrated circuits", "bit error rate", "distance 2 m", "frequency 200 GHz to 300 GHz", "frequency 220 GHz", "millimeter-wave transmit frontend", "quadrature amplitude modulation transmission", "receive frontend", "size 50 nm", "split-block waveguide modules", "wireless data link", "FET integrated circuits", "Frequency control", "Frequency conversion", "Gain", "MMICs", "Receivers", "Wireless communication", "220 GHz", "Millimeter-wave amplification", "millimeter-wave FET integrated circuits", "millimeter-wave frequency conversion", "millimeter-wave monolithic integrated circuits (MMICs)", "wireless communication", ""], "arnumber": "5971794"}