{"citations": ["1368149", "1597401", "6988163", "6228813"], "references": [], "details": {"publisher": "IEEE", "issue_date": "Feb 2001", "doi": "10.1109/62.904242", "title": "The problem with aviation COTS", "abstract": "Commercial Off the Shelf (COTS) has become a byword for acquisition reform, but there are significant risks associated with the use of COTS products in military systems. These risks are especially acute for aviation systems. This paper explains how COTS can negatively affect military acquisitions and gives ideas on how to plan and resolve COTS caused problems", "journal_title": "IEEE Aerospace and Electronic Systems Magazine", "firstpage": "33", "volume": "16", "lastpage": "37", "date_publication": "Feb 2001", "inspec": "6861709", "date": "Feb 2001", "date_current_version": "Wed Aug 07 00:00:00 EDT 2002", "issue": "2", "pages": "33 - 37", "issn": "0885-8985"}, "authors": ["L. D. Alford"], "keywords": ["aircraft computers", "equipment selection", "life cycle costing", "logistics data processing", "military avionics", "purchasing", "COTS products", "acquisition reform", "aviation COTS problem", "cost distribution", "forced modifications", "life cycle cost", "military acquisitions", "military systems", "obsolescence", "procurement", "purchasing", "Aircraft manufacture", "Costs", "Defense industry", "Documentation", "Manufacturing", "Procurement", "Protection", "Research and development", "Tail", "US Government", ""], "arnumber": "904242"}