{"citations": [], "references": [], "details": {"publisher": "IEEE", "issue_date": "Aug. 1993", "doi": "10.1109/62.248328", "title": "Reliability Technology to Achieve Insertion of Advanced Packaging (RELTECH) program", "abstract": null, "journal_title": "IEEE Aerospace and Electronic Systems Magazine", "firstpage": "32", "volume": "8", "lastpage": "38", "date_publication": "Aug. 1993", "inspec": "4516442", "date": "Aug. 1993", "date_current_version": "Tue Aug 06 00:00:00 EDT 2002", "issue": "8", "pages": "32 - 38", "issn": "0885-8985"}, "authors": ["D. F. Fayette", "P. Speicher", "M. J. Stoklosa", "J. V. Evans", "J. W. Evans", "M. Gentile", "C. A. Pagel", "E. Hakim"], "keywords": ["electronic equipment testing", "hybrid integrated circuits", "integrated circuit testing", "multichip modules", "production testing", "reliability", "standardisation", "MIL-H-38534 general specification", "accelerated testing", "environmental testing", "failure analysis", "failure mechanisms", "hybrid microcircuits", "joint military-commercial effort", "multichip module", "packaging", "post-test physical analysis", "product evaluation", "reliability modeling", "standardization", "Costs", "Failure analysis", "Hybrid integrated circuits", "Life estimation", "Multichip modules", "Packaging", "Qualifications", "Standardization", "Testing", "Vehicles", ""], "arnumber": "248328"}