{"citations": [], "references": ["119564"], "details": {"publisher": "IEEE", "issue_date": "Oct. 2003", "doi": "10.1109/TAES.2003.1261130", "title": "Submarine floating antenna model for LORAN-C signal processing", "abstract": "An electromagnetic model of the floating antenna used by submarines for LORAN-C radionavigation and very low frequency (VLF) communications is proposed. We present a description of the floating antenna and analyze its electric characteristics. The current in the horizontal wire induced by the lateral wave is then computed and we suggest a model that yields to a nonrational transfer function. A parameter estimation algorithm based on parallel-extended Kalman filters is then proposed and validated on real data.", "journal_title": "IEEE Transactions on Aerospace and Electronic Systems", "firstpage": "1304", "volume": "39", "lastpage": "1315", "date_publication": "Oct. 2003", "sponsor": "Aerospace & Electronic Systems Society", "inspec": "7879935", "date": "Oct. 2003", "date_current_version": "Wed Jan 21 00:00:00 EST 2004", "issue": "4", "pages": "1304 - 1315", "issn": "0018-9251"}, "authors": ["A. Monin"], "keywords": ["Kalman filters", "parameter estimation", "radionavigation", "underwater vehicles", "wire antennas", "LORAN-C radionavigation", "LORAN-C signal processing", "VLF communication", "electromagnetic model", "nonrational transfer function", "parallel-extended Kalman filter", "parameter estimation algorithm", "submarine floating antenna model", "very low frequency", "Electric variables", "Electromagnetic modeling", "Electromagnetic scattering", "Frequency", "Optical transmitters", "Parameter estimation", "Signal processing", "Transfer functions", "Underwater vehicles", "Wire", ""], "arnumber": "1261130"}