{"arnumber": "4118435", "details": {"title": "Corrections to \"Challenges related to reliability in nano electronics\"", "volume": "56", "keywords": [{"type": "IEEE Keywords", "kwd": ["Costs", "Plasma displays", "Life estimation", "Physics computing", "Nanotechnology Council"]}, {"type": "INSPEC: Controlled Indexing", "kwd": ["reliability", "nanoelectronics"]}, {"type": "INSPEC: Non-Controlled Indexing", "kwd": ["nanoelectronics", "reliability"]}], "issue": "1", "link": "http://ieeexplore.ieee.org/servlet/opac?punumber=24", "authors": [{"name": "W. Kuo"}], "publisher": "IEEE", "doi": "10.1109/TR.2006.890224", "abstract": "The author makes two modifications to his original paper (see ibid., vol.55, no.4, p.569-70, Dec. 2006)."}, "references": [{"title": "Challenges related to reliability in nano electronics", "context": [{"text": "In the above paper [1], there are two modifications.", "sec": "", "part": ""}, {"text": " Under section heading, \u201cReliability and Nano Technologies\u201d [1, p. 569], the sentence \u201cFor example, are consumers likely to be satisfied with high cost plasma TVs with an estimated 4\u2013year expected life?\u201d should read \u201cFor example, are consumers likely to be satisfied with high cost plasma TVs with an estimated 5-7 year expected life?\u201d.", "sec": "", "part": ""}, {"text": " Under sub-section heading, \u201cManagement of the Scarcity and Secrecy of Available Data\u201d [1, p. 570], the following two sentences are added at the end of the second paragraph from the end\u2014The other possibility, with great challenge too, is to predict reliability using the computer-aided tools, based on the physical properties of the nano systems.", "sec": "", "part": ""}], "order": "1", "links": {"openUrlImgLoc": "/assets/img/btn.find-in-library.png", "abstract": "Abs", "documentLink": "/document/4016402", "pdfLink": "/stamp/stamp.jsp?tp=&arnumber=4016402", "pdfSize": "39KB"}, "id": "ref1", "text": "W. Kuo, \"Challenges related to reliability in nano electronics\", <em>IEEE Trans. Rel.</em>, vol. 55, no. 4, pp. 569-570, Dec. 2006.", "refType": "biblio"}], "citations": {"paperCitations": {}, "patentCitationCount": "0", "contentType": "periodicals", "isEarlyAccess": false, "lastupdate": "2016-11-12T02:00:45", "publisher": "IEEE", "title": "Corrections to \"Challenges related to reliability in nano electronics\"", "nonIeeeCitationCount": "0", "publicationNumber": "24", "formulaStrippedArticleTitle": "Corrections to \"Challenges related to reliability in nano electronics\"", "mediaPath": "/mediastore/IEEE/content/media/24/4118420/4118435", "mlTime": "PT0.01967S", "ieeeCitationCount": "0"}}