{"arnumber": "6526685", "details": {"isCustomDenial": false, "isConference": false, "subType": "IET IEE Periodical", "issueLink": "/xpl/tocresult.jsp?isnumber=6526675", "authors": [{"name": "Stefano Fortunati", "affiliation": "University of Pisa, Italy"}, {"name": "Fulvio Gini", "affiliation": "University of Pisa, Italy"}, {"name": "Alfonso Farina", "affiliation": "SELEX ES, Italy"}, {"name": "Antonio Graziano", "affiliation": "SELEX ES, Italy"}, {"name": "Maria S. Greco", "affiliation": "University of Pisa, Italy"}, {"name": "Sofia Giompapa", "affiliation": "SELEX ES, Italy"}], "pubLink": "/xpl/RecentIssue.jsp?punumber=4119394", "startPage": "191", "contentType": "periodicals", "pdfPath": "/iel7/4119394/6526675/06526685.pdf", "conferenceDate": " ", "lastupdate": "2014-10-13T16:03:29", "mlTime": "PT0.045542S", "publicationNumber": "4119394", "formulaStrippedArticleTitle": "On the application of the expectation-maximisation algorithm to the relative sensor registration problem", "title": "On the application of the expectation-maximisation algorithm to the relative sensor registration problem", "chronOrPublicationDate": "February 2013", "mediaPath": "/mediastore/IEEE/content/media/4119394/6526675/6526685", "isNumber": "6526675", "standardTitle": "On the application of the expectation-maximisation algorithm to the relative sensor registration problem", "isEphemera": false, "ephemeraFlag": "false", "allowComments": false, "isStaticHtml": false, "sections": {"disclaimer": "false", "references": "false", "multimedia": "false", "footnotes": "false", "abstract": "true", "keywords": "true", "authors": "true", "citedby": "true", "figures": "false"}, "isACM": false, "copyrightOwner": "IET", "publicationTitle": "IET Radar, Sonar & Navigation", "persistentLink": "http://ieeexplore.ieee.org/servlet/opac?punumber=4119394", "openAccessFlag": "no", "volume": "7", "isJournal": true, "isNotDynamicOrStatic": true, "displayPublicationTitle": "IET Radar, Sonar & Navigation", "rightsLink": "http://s100.copyright.com/AppDispatchServlet?publisherName=ieee&publication=1751-8784&title=On+the+application+of+the+expectation-maximisation+algorithm+to+the+relative+sensor+registration+problem&isbn=&publicationDate=February+2013&author=Stefano+Fortunati&ContentID=10.1049/iet-rsn.2012.0050&orderBeanReset=true&startPage=191&endPage=203&volumeNum=7&issueNum=2", "isStandard": false, "endPage": "203", "abstract": "An important prerequisite for successful multisensor integration is that the data from the reporting sensors are transformed to a common reference frame free of systematic or registration bias errors. The relative sensor registration (or grid-locking) process aligns remote data to local data under the assumption that the local data are bias free and that all biases reside with the remote sensor. In this study, an algorithm based on the expectation-maximisation approach is proposed to estimate all the registration errors involved in the grid-locking problem, that is, attitude, measurement and position biases. Its statistical performance is investigated by Monte Carlo simulation and compared with that of a previously derived linear least squares estimator and to the hybrid Cram\u00e9r-Rao lower bound.", "isPromo": false, "publicationDate": "February 2013", "copyrightYear": "2007-2012", "isOpenAccess": false, "publisher": "IET", "articleId": "6526685", "issue": "2", "isDynamicHtml": false, "citationCount": "2", "htmlAbstractLink": "/document/6526685/", "doi": "10.1049/iet-rsn.2012.0050", "accessionNumber": "", "issn": [{"format": "Print ISSN", "value": "1751-8784"}, {"format": "Online ISSN", "value": "1751-8792"}], "isSMPTE": false, "articleNumber": "6526685", "userInfo": {"institute": false, "individual": false, "showPatentCitations": true, "guest": false, "member": false, "fileCabinetUser": false, "fileCabinetContent": false, "showOpenUrlLink": false, "subscribedContent": false, "showGet802Link": false}, "isBook": false, "isFreeDocument": false, "isEarlyAccess": false}, "references": [], "citations": {"contentType": "periodicals", "mediaPath": "/mediastore/IEEE/content/media/4119394/6526675/6526685", "publisher": "IET", "ieeeCitationCount": "2", "paperCitations": {"ieee": [{"links": {"pdfLink": "/stamp/stamp.jsp?tp=&arnumber=7472955", "pdfSize": "1676KB", "documentLink": "/document/7472955", "openUrlImgLoc": "/assets/img/btn.find-in-library.png"}, "order": "1", "displayText": "Jianxin Yi, Xianrong Wan, Henry Leung, Min Lu, Feng Cheng, \"Noncooperative registration for multistatic passive radars\", <em>Aerospace and Electronic Systems IEEE Transactions on</em>, vol. 52, pp. 563-575, 2016, ISSN 0018-9251.", "title": "Noncooperative registration for multistatic passive radars"}, {"links": {"pdfLink": "/stamp/stamp.jsp?tp=&arnumber=7801151", "pdfSize": "328KB", "documentLink": "/document/7801151", "openUrlImgLoc": "/assets/img/btn.find-in-library.png"}, "order": "2", "displayText": "Nabil Kbayer, J&#x00E9;r&#x00F4;me Galy, Eric Chaumette, Fran&#x00E7;ois Vincent, Alexandre Renaux, Pascal Larzabal, \"On Lower Bounds for Nonstandard Deterministic Estimation\", <em>Signal Processing IEEE Transactions on</em>, vol. 65, pp. 1538-1553, 2017, ISSN 1053-587X.", "title": "On Lower Bounds for Nonstandard Deterministic Estimation"}]}, "isEarlyAccess": false, "lastupdate": "2014-10-13T16:03:29", "mlTime": "PT0.041804S", "publicationNumber": "4119394", "formulaStrippedArticleTitle": "On the application of the expectation-maximisation algorithm to the relative sensor registration problem", "nonIeeeCitationCount": "0", "patentCitationCount": "0", "title": "On the application of the expectation-maximisation algorithm to the relative sensor registration problem"}}