{"arnumber": "7070614", "details": {"title": "Robust direction of arrival estimate method in FM-based passive bistatic radar with a four-element Adcock antenna array", "volume": "9", "keywords": [{"type": "INSPEC: Controlled Indexing", "kwd": ["radar detection", "antenna arrays", "direction-of-arrival estimation", "FM radar", "object detection", "passive radar", "radar antennas", "radar cross-sections"]}, {"type": "INSPEC: Non-Controlled Indexing", "kwd": ["four-element Adcock antenna array", "robust DOA estimation", "FM-based passive bistatic radar", "direction-of-arrival estimate method", "target detection", "target echo"]}], "issue": "4", "link": "http://ieeexplore.ieee.org/servlet/opac?punumber=4119394", "authors": [{"affiliation": "Xidian University, People's Republic of China", "name": "Lv Xiao-Yong"}, {"affiliation": "Xidian University, People's Republic of China", "name": "Wang Jun"}, {"affiliation": "Xidian University, People's Republic of China", "name": "Wang Jue"}], "publisher": "IET", "doi": "10.1049/iet-rsn.2014.0270", "abstract": "This study examines the problem of direction of arrival (DOA) estimation in FM-based passive bistatic radar using a four-element Adcock antenna array. The authors investigate the influence of the target echo, involved in the reference signal, on the DOA estimation of the corresponding target considered. Analysis shows that, unlike the pure reference signal case, a weak target echo involved in the reference signal may not affect the detection of the corresponding target. It can often have a significant impact on the estimation of a target's DOA; thus typical DOA estimate methods degrade heavily. A robust method is proposed to cope with this problem. Simulation and experimental results demonstrate the effectiveness of the method."}, "references": [], "citations": {"paperCitations": {"ieee": [{"links": {"openUrlImgLoc": "/assets/img/btn.find-in-library.png", "documentLink": "/document/7411873", "pdfLink": "/stamp/stamp.jsp?tp=&arnumber=7411873", "pdfSize": "652KB"}, "title": "Disturbance removal in passive radar via sliding extensive cancellation algorithm (ECA-S)", "displayText": "C. Palmarini, T. Martelli, F. Colone, P. Lombardo, \"Disturbance removal in passive radar via sliding extensive cancellation algorithm (ECA-S)\", <em>Radar Conference 2015 IEEE</em>, pp. 162-167, 2015.", "order": "1"}, {"links": {"openUrlImgLoc": "/assets/img/btn.find-in-library.png", "documentLink": "/document/7511860", "pdfLink": "/stamp/stamp.jsp?tp=&arnumber=7511860", "pdfSize": "1981KB"}, "title": "Sliding extensive cancellation algorithm for disturbance removal in passive radar", "displayText": "Fabiola Colone, Claudio Palmarini, Tatiana Martelli, Enrico Tilli, \"Sliding extensive cancellation algorithm for disturbance removal in passive radar\", <em>Aerospace and Electronic Systems IEEE Transactions on</em>, vol. 52, pp. 1309-1326, 2016, ISSN 0018-9251.", "order": "2"}]}, "patentCitationCount": "0", "contentType": "periodicals", "isEarlyAccess": false, "lastupdate": "2016-10-22T09:05:54", "publisher": "IET", "title": "Robust direction of arrival estimate method in FM-based passive bistatic radar with a four-element Adcock antenna array", "nonIeeeCitationCount": "0", "mlTime": "PT0.026798S", "formulaStrippedArticleTitle": "Robust direction of arrival estimate method in FM-based passive bistatic radar with a four-element Adcock antenna array", "mediaPath": "/mediastore/IEEE/content/media/4119394/7070506/7070614", "publicationNumber": "4119394", "ieeeCitationCount": "2"}}