{"citations": [], "references": [], "details": {"publisher": "IET", "issue_date": "1881", "doi": "10.1049/jste-2.1881.0025", "title": "Letter regarding currents produced in a wire by flowing water", "abstract": "", "journal_title": "Telegraph Engineers and of Electricians, Journal of the Society of", "firstpage": "277", "volume": "10", "lastpage": "278", "date_publication": "1881", "date": "1881", "date_current_version": "Fri Jan 29 00:00:00 EST 2010", "issue": "37", "pages": "277 - 278"}, "authors": ["C. E. Spagnoletti"], "keywords": [], "arnumber": "5300372"}