{"citations": ["6853330", "6933336", "7279552", "7364982", "7279675"], "references": ["1458289", "1200430", "4653448", "4103057", "4104017", "1165266", "1145217", "1165089", "1145216", "4107538", "102710", "328767", "259534", "301830", "543864", "886153", "1662471", "4489086", "5425667", "966097", "1275684", "940014", "983917", "1266069", "4343996", "1458275", "1458287", "1458284", "1458273", "231342", "1611085", "1683188", "4145280", "1413222", "4510769", "1703954", "4569986"], "details": {"publisher": "IEEE", "issue_date": "Aug. 2013", "doi": "10.1109/MAES.2013.6575420", "title": "Review of range-based positioning algorithms", "abstract": "This tutorial reviews algorithms which turn measured ranges into position solutions. From their basic mathematical principles, we relate and compare relevant aspects of these algorithms. Special attention is given to the direct (non-iterative) algorithms, which are frequently applied in indoor positioning. Most of them are shown to be essentially the same, as they can be related through applying different weighting schemes. This tutorial is intended as a useful guide to help researchers and system designers evaluate and select appropriate range-based positioning algorithms for their applications at hand.", "journal_title": "IEEE Aerospace and Electronic Systems Magazine", "firstpage": "2", "volume": "28", "lastpage": "27", "date_publication": "Aug. 2013", "inspec": "13684754", "date": "Aug. 2013", "date_current_version": "Wed Aug 07 00:00:00 EDT 2013", "issue": "8", "pages": "2 - 27", "issn": "0885-8985"}, "authors": ["Junlin Yan", "Christian C. J. M. Tiberius", "Gerard J. M. Janssen", "Peter J. G. Teunissen", "Giovanni Bellusci"], "keywords": ["Global Positioning System", "mathematical analysis", "indoor positioning", "mathematical principle", "range-based positioning algorithm", "Algorithm design and analysis", "Algorithms", "Position measurement", "Tutorials", ""], "arnumber": "6575420"}